hx_shi.py
hx_rk1-1.0.dist-info/METADATA
hx_rk1-1.0.dist-info/WHEEL
hx_rk1-1.0.dist-info/top_level.txt
hx_rk1-1.0.dist-info/RECORD
