Metadata-Version: 2.1
Name: hx-rk1
Version: 1.0
Summary: 大数据1小石的终极版，
Home-page: UNKNOWN
Author: 小石
Author-email: 480523858@qq.com
License: UNKNOWN
Platform: UNKNOWN
